regex/__init__.py
regex/_regex.cpython-312.so
regex/_regex_core.py
regex/regex.py
regex/test_regex.py
regex_qpython-2024.11.6.1.dist-info/METADATA
regex_qpython-2024.11.6.1.dist-info/WHEEL
regex_qpython-2024.11.6.1.dist-info/top_level.txt
regex_qpython-2024.11.6.1.dist-info/RECORD
